Workbook

Sheet Dashboard
A1: BUDGET & COST TRACKER — Government Contract Remote Surge Hiring
A2: Prepared for Kelly | Generated: 20 April 2026 | Plain Dealing, LA
A4: EXECUTIVE SUMMARY
A5: Total Budget | B5: Total Spent | C5: Remaining Budget | D5: Burn Rate ($/day) | E5: Projected Final Cost | F5: Variance ($)
A6: ='Variance Report'!B10 | B6: ='Variance Report'!C10 | C6: ='Variance Report'!D10 | D6: =IF('Expenditure Log'!A22="",0,'Expenditure Log'!M22/('Expenditure Log'!A22-'Expenditure Log'!A3)) | E6: ='Forecast'!B31 | F6: ='Variance Report'!D10
A7: Variance (%) | B7: ='Variance Report'!E10 | C7: Overall Status | D7: =IF(B7<0,"OVER BUDGET",IF(B7<=0.1,"ON TRACK","UNDER BUDGET")) | E7: Cost Per Hire | F7: ='Cost Per Hire Analysis'!B22
A9: COST BREAKDOWN BY CATEGORY
A10: Category | B10: Budgeted | C10: Actual | D10: Variance ($) | E10: Variance (%) | F10: Status
A11: Recruiting | B11: ='Variance Report'!B3 | C11: ='Variance Report'!C3 | D11: ='Variance Report'!D3 | E11: ='Variance Report'!E3 | F11: ='Variance Report'!F3
A12: Equipment/IT | B12: ='Variance Report'!B4 | C12: ='Variance Report'!C4 | D12: ='Variance Report'!D4 | E12: ='Variance Report'!E4 | F12: ='Variance Report'!F4
A13: Training | B13: ='Variance Report'!B5 | C13: ='Variance Report'!C5 | D13: ='Variance Report'!D5 | E13: ='Variance Report'!E5 | F13: ='Variance Report'!F5
A14: Personnel | B14: ='Variance Report'!B6 | C14: ='Variance Report'!C6 | D14: ='Variance Report'!D6 | E14: ='Variance Report'!E6 | F14: ='Variance Report'!F6
A15: Background/Clearance | B15: ='Variance Report'!B7 | C15: ='Variance Report'!C7 | D15: ='Variance Report'!D7 | E15: ='Variance Report'!E7 | F15: ='Variance Report'!F7
A16: Overhead | B16: ='Variance Report'!B8 | C16: ='Variance Report'!C8 | D16: ='Variance Report'!D8 | E16: ='Variance Report'!E8 | F16: ='Variance Report'!F8
A17: Contingency | B17: ='Variance Report'!B9 | C17: ='Variance Report'!C9 | D17: ='Variance Report'!D9 | E17: ='Variance Report'!E9 | F17: ='Variance Report'!F9
A19: BUDGET vs ACTUAL BY PHASE
A20: Phase | B20: Budgeted | C20: Actual | D20: Variance ($) | E20: Variance (%) | F20: Status
A21: Pre-Planning | B21: 25000 | C21: 18500 | D21: =B21-C21 | E21: =IF(B21=0,0,D21/B21) | F21: =IF(D21<0,"Over Budget",IF(E21<=0.1,"On Track","Under Budget"))
A22: Activation | B22: 85000 | C22: 78300 | D22: =B22-C22 | E22: =IF(B22=0,0,D22/B22) | F22: =IF(D22<0,"Over Budget",IF(E22<=0.1,"On Track","Under Budget"))
A23: Onboarding | B23: 150000 | C23: 142900 | D23: =B23-C23 | E23: =IF(B23=0,0,D23/B23) | F23: =IF(D23<0,"Over Budget",IF(E23<=0.1,"On Track","Under Budget"))
A24: Sustain | B24: 180000 | C24: 0 | D24: =B24-C24 | E24: =IF(B24=0,0,D24/B24) | F24: =IF(D24<0,"Over Budget",IF(E24<=0.1,"On Track","Under Budget"))
A25: Close-Out | B25: 30000 | C25: 0 | D25: =B25-C25 | E25: =IF(B25=0,0,D25/B25) | F25: =IF(D25<0,"Over Budget",IF(E25<=0.1,"On Track","Under Budget"))
A27: MONTHLY BURN RATE TREND | H27: TRAFFIC LIGHT LEGEND
A28: Month | B28: Planned Spend | C28: Actual Spend | D28: Cumulative Actual | H28: ● | I28: Green — Under Budget (>10% remaining)
A29: Month 1 | B29: =Forecast!D11 | C29: =Forecast!D20 | D29: =C29 | H29: ● | I29: Yellow — On Track (within 10%)
A30: Month 2 | B30: =Forecast!E11 | C30: =Forecast!E20 | D30: =D29+C30 | H30: ● | I30: Red — Over Budget (exceeds budget)
A31: Month 3 | B31: =Forecast!F11 | C31: =Forecast!F20 | D31: =D30+C31
A32: Month 4 | B32: =Forecast!G11 | C32: =Forecast!G20 | D32: =D31+C32
A33: Month 5 | B33: =Forecast!H11 | C33: =Forecast!H20 | D33: =D32+C33
A34: Month 6 | B34: =Forecast!I11 | C34: =Forecast!I20 | D34: =D33+C34
A35: Month 7 | B35: =Forecast!J11 | C35: =Forecast!J20 | D35: =D34+C35
A36: Month 8 | B36: =Forecast!K11 | C36: =Forecast!K20 | D36: =D35+C36
A37: Month 9 | B37: =Forecast!L11 | C37: =Forecast!L20 | D37: =D36+C37
A38: Month 10 | B38: =Forecast!M11 | C38: =Forecast!M20 | D38: =D37+C38
A39: Month 11 | B39: =Forecast!N11 | C39: =Forecast!N20 | D39: =D38+C39
A40: Month 12 | B40: =Forecast!O11 | C40: =Forecast!O20 | D40: =D39+C40

Sheet Budget Plan
A1: Budget Plan — Government Contract Remote Surge Hiring
A2: Line Item | B2: Category | C2: Description | D2: Unit Cost | E2: Quantity | F2: Total Budgeted | G2: Approved By | H2: Approval Date | I2: Notes
A3: Job Board Postings (USAJobs, ClearanceJobs) | B3: Recruiting | C3: Annual posting fees for multiple job boards | D3: 2500 | E3: 6 | F3: =D3*E3
A4: Recruiter Hours — Internal | B4: Recruiting | C4: Dedicated recruiter FTE hours for surge | D4: 75 | E4: 480 | F4: =D4*E4
A5: Assessment Tools & Licensing | B5: Recruiting | C5: Pre-hire cognitive and skills assessment platform | D5: 15 | E5: 200 | F5: =D5*E5
A6: Travel for Interviews | B6: Recruiting | C6: Candidate travel reimbursement for in-person interviews | D6: 800 | E6: 10 | F6: =D6*E6
A7: Referral Bonuses | B7: Recruiting | C7: Employee referral bonus per successful hire | D7: 1500 | E7: 20 | F7: =D7*E7
A8: Staffing Agency Fees | B8: Recruiting | C8: Third-party staffing agency placement fees | D8: 5000 | E8: 10 | F8: =D8*E8
A9: Laptops (Gov-Spec) | B9: Equipment/IT | C9: FIPS 140-2 compliant laptops with encryption | D9: 1800 | E9: 50 | F9: =D9*E9
A10: External Monitors | B10: Equipment/IT | C10: 24-inch IPS monitors for remote workstations | D10: 350 | E10: 50 | F10: =D10*E10
A11: Headsets (VOIP-Compatible) | B11: Equipment/IT | C11: Noise-cancelling USB headsets | D11: 120 | E11: 50 | F11: =D11*E11
A12: CAC Readers | B12: Equipment/IT | C12: USB smart card readers for PIV/CAC authentication | D12: 45 | E12: 55 | F12: =D12*E12
A13: Keyboards & Mice Kits | B13: Equipment/IT | C13: Ergonomic keyboard and mouse combo | D13: 80 | E13: 50 | F13: =D13*E13
A14: Webcams (HD Secure) | B14: Equipment/IT | C14: 1080p webcams with privacy shutters | D14: 95 | E14: 50 | F14: =D14*E14
... A34: Facilities / Hoteling Space | B34: Overhead | C34: Shared desk/hoteling reservations for hybrid workers | D34: 500 | E34: 20 | F34: =D34*E34
A35: Contingency Reserve (10%) | B35: Contingency | C35: 10% contingency on total budgeted amount | D35: 1 | E35: 1 | F35: =ROUND((SUMPRODUCT(D3:D34,E3:E34))*0.10,2)
A38: CATEGORY SUMMARY
A39: Category | B39: Total Budgeted
A40: Recruiting | B40: =SUMIFS(F3:F35,B3:B35,A40)
A41: Equipment/IT | B41: =SUMIFS(F3:F35,B3:B35,A41)
A42: Training | B42: =SUMIFS(F3:F35,B3:B35,A42)
A43: Personnel | B43: =SUMIFS(F3:F35,B3:B35,A43)
A44: Background/Clearance | B44: =SUMIFS(F3:F35,B3:B35,A44)
A45: Overhead | B45: =SUMIFS(F3:F35,B3:B35,A45)
A46: Contingency | B46: =SUMIFS(F3:F35,B3:B35,A46)
A47: GRAND TOTAL | B47: =SUM(B40:B46)

Sheet Expenditure Log
A1: Expenditure Log — Surge Hiring Operations
A2: Date | B2: Vendor/Payee | C2: Description | D2: Category | E2: Line Item Reference | F2: Invoice Number | G2: Amount | H2: Payment Method | I2: Payment Status | J2: Approved By | K2: GL Code | L2: Contract CLIN | M2: Running Total | N2: Notes
A3: 46027 | B3: ClearanceJobs.com | C3: Q1 Job Board Posting Package | D3: Recruiting | E3: Job Board Postings | F3: INV-10001 | G3: 2500 | H3: Invoice | I3: Paid | J3: J. Martinez | K3: 6100-01 | L3: CLIN 0001 | M3: =SUM(G3:G3)
A4: 46030 | B4: Dell Technologies | C4: Lot 1 — 20x Latitude 5540 Laptops | D4: Equipment/IT | E4: Laptops (Gov-Spec) | F4: INV-10002 | G4: 36000 | H4: Invoice | I4: Paid | J4: J. Martinez | K4: 6200-01 | L4: CLIN 0002 | M4: =SUM(G3:G4)
A5: 46032 | B5: Amazon Business | C5: 20x USB Headsets — Jabra Evolve2 | D5: Equipment/IT | E5: Headsets (VOIP-Compatible) | F5: INV-10003 | G5: 2400 | H5: P-Card | I5: Paid | J5: S. Nguyen | K5: 6200-02 | L5: CLIN 0002 | M5: =SUM(G3:G5)
A6: 46034 | B6: HireVue Inc. | C6: Assessment Platform — 100 seat license | D6: Recruiting | E6: Assessment Tools & Licensing | F6: INV-10004 | G6: 3000 | H6: Invoice | I6: Paid | J6: J. Martinez | K6: 6100-02 | L6: CLIN 0001 | M6: =SUM(G3:G6)
A7: 46037 | B7: CACI International | C7: Staffing Agency — 3 placements | D7: Recruiting | E7: Staffing Agency Fees | F7: INV-10005 | G7: 15000 | H7: Invoice | I7: Paid | J7: R. Thompson | K7: 6100-03 | L7: CLIN 0001 | M7: =SUM(G3:G7)
A8: 46042 | B8: Cornerstone OnDemand | C8: LMS Licenses — 60 seats | D8: Training | E8: LMS Licenses | F8: INV-10006 | G8: 3000 | H8: Invoice | I8: Approved | J8: S. Nguyen | K8: 6300-01 | L8: CLIN 0003 | M8: =SUM(G3:G8)
A9: 46054 | B9: Internal Payroll | C9: Recruiter OT — Jan cycle | D9: Personnel | E9: Overtime — Existing Staff | F9: PAY-20001 | G9: 4800 | H9: ACH | I9: Paid | J9: R. Thompson | K9: 6400-01 | L9: CLIN 0004 | M9: =SUM(G3:G9)
A10: 46058 | B10: DCSA/OPM | C10: e-QIP Processing — Batch 1 (20 applicants) | D10: Background/Clearance | E10: e-QIP Processing Fees | F10: GOV-30001 | G10: 7000 | H10: Check | I10: Paid | J10: J. Martinez | K10: 6500-01 | L10: CLIN 0005 | M10: =SUM(G3:G10)
A11: 46063 | B11: Quest Diagnostics | C11: Drug Screening — 25 candidates | D11: Background/Clearance | E11: Drug Testing | F11: INV-10007 | G11: 2125 | H11: P-Card | I11: Paid | J11: S. Nguyen | K11: 6500-02 | L11: CLIN 0005 | M11: =SUM(G3:G11)
A12: 46068 | B12: FedEx | C12: Equipment Shipping — Batch 1 | D12: Equipment/IT | E12: Shipping & Logistics | F12: INV-10008 | G12: 1300 | H12: P-Card | I12: Paid | J12: S. Nguyen | K12: 6200-03 | L12: CLIN 0002 | M12: =SUM(G3:G12)
A13: 46073 | B13: Cisco Systems | C13: VPN Licenses — 55 users | D13: Overhead | E13: VPN & Remote Access Licenses | F13: INV-10009 | G13: 6600 | H13: Invoice | I13: Approved | J13: R. Thompson | K13: 6600-01 | L13: CLIN 0006 | M13: =SUM(G3:G13)
A14: 46082 | B14: Booz Allen Hamilton | C14: Contract Instructor — Week 1 | D14: Training | E14: Instructor / Facilitator Costs | F14: INV-10010 | G14: 6000 | H14: Invoice | I14: Paid | J14: J. Martinez | K14: 6300-02 | L14: CLIN 0003 | M14: =SUM(G3:G14)
A15: 46086 | B15: Internal Payroll | C15: New Hire Salaries — Ramp Cohort 1 (15) | D15: Personnel | E15: Salary Costs — Ramp Period | F15: PAY-20002 | G15: 67500 | H15: ACH | I15: Paid | J15: R. Thompson | K15: 6400-02 | L15: CLIN 0004 | M15: =SUM(G3:G15)
A16: 46091 | B16: IdentoGO | C16: Fingerprinting — 30 applicants | D16: Background/Clearance | E16: Fingerprinting (Live Scan) | F16: INV-10011 | G16: 1500 | H16: P-Card | I16: Pending | J16: S. Nguyen | K16: 6500-03 | L16: CLIN 0005 | M16: =SUM(G3:G16)
A17: 46096 | B17: Microsoft | C17: Teams E5 Licenses — 55 seats | D17: Overhead | E17: Collaboration Tools (MS Teams/Zoom) | F17: INV-10012 | G17: 1650 | H17: Invoice | I17: Paid | J17: R. Thompson | K17: 6600-02 | L17: CLIN 0006 | M17: =SUM(G3:G17)
A18: 46101 | B18: CompTIA | C18: Security+ Exam Vouchers — 15 | D18: Training | E18: Certification Exam Fees | F18: INV-10013 | G18: 6000 | H18: Invoice | I18: Disputed | J18: J. Martinez | K18: 6300-03 | L18: CLIN 0003 | M18: =SUM(G3:G18)
A19: 46113 | B19: Dell Technologies | C19: Lot 2 — 15x Monitors + Peripherals | D19: Equipment/IT | E19: External Monitors | F19: INV-10014 | G19: 5250 | H19: Invoice | I19: Pending | J19: S. Nguyen | K19: 6200-04 | L19: CLIN 0002 | M19: =SUM(G3:G19)
A20: 46117 | B20: Internal Payroll | C20: New Hire Salaries — Ramp Cohort 2 (10) | D20: Personnel | E20: Salary Costs — Ramp Period | F20: PAY-20003 | G20: 45000 | H20: ACH | I20: Approved | J20: R. Thompson | K20: 6400-02 | L20: CLIN 0004 | M20: =SUM(G3:G20)
A21: 46122 | B21: Polygraph Associates LLC | C21: Full-Scope Poly — 5 candidates | D21: Background/Clearance | E21: Polygraph Examinations | F21: INV-10015 | G21: 12500 | H21: Invoice | I21: Pending | J21: J. Martinez | K21: 6500-04 | L21: CLIN 0005 | M21: =SUM(G3:G21)
A22: 46127 | B22: WeWork | C22: Hoteling — 10 desks x 2 months | D22: Overhead | E22: Facilities / Hoteling Space | F22: INV-10016 | G22: 10000 | H22: Invoice | I22: Approved | J22: R. Thompson | K22: 6600-03 | L22: CLIN 0006 | M22: =SUM(G3:G22)

Sheet Cost Per Hire Analysis
A1: Cost Per Hire Analysis — Surge Hiring Operation
A2: Employee Name | B2: Position | C2: Clearance Level | D2: Start Date | E2: Recruiting Cost | F2: Background/Clearance Cost | G2: Equipment Cost | H2: Training Cost | I2: Onboarding Cost | J2: Total Cost to Hire | K2: Days to Fill | L2: Cost Per Day
A3: Adams, Sarah | B3: IT Specialist | C3: Secret | D3: 46063 | E3: 3200 | F3: 1450 | G3: 2540 | H3: 1800 | I3: 500 | J3: =SUM(E3:I3) | K3: 45 | L3: =IF(K3=0,0,J3/K3)
A4: Brooks, James | B4: Cybersecurity Analyst | C4: TS/SCI | D4: 46068 | E4: 4500 | F4: 3850 | G4: 2540 | H4: 2200 | I4: 600 | J4: =SUM(E4:I4) | K4: 62 | L4: =IF(K4=0,0,J4/K4)
A5: Chen, Wei | B5: Help Desk Technician | C5: Public Trust | D5: 46071 | E5: 1800 | F5: 485 | G5: 2340 | H5: 1200 | I5: 400 | J5: =SUM(E5:I5) | K5: 28 | L5: =IF(K5=0,0,J5/K5)
A6: Davis, Marcus | B6: Systems Administrator | C6: Secret | D6: 46077 | E6: 3500 | F6: 1450 | G6: 2540 | H6: 1800 | I6: 500 | J6: =SUM(E6:I6) | K6: 38 | L6: =IF(K6=0,0,J6/K6)
A7: Evans, Patricia | B7: Network Engineer | C7: TS/SCI | D7: 46083 | E7: 5200 | F7: 3850 | G7: 2740 | H7: 2200 | I7: 650 | J7: =SUM(E7:I7) | K7: 70 | L7: =IF(K7=0,0,J7/K7)
A8: Foster, Andre | B8: Program Analyst | C8: Secret | D8: 46086 | E8: 2800 | F8: 1450 | G8: 2340 | H8: 1500 | I8: 450 | J8: =SUM(E8:I8) | K8: 35 | L8: =IF(K8=0,0,J8/K8)
A9: Garcia, Maria | B9: Data Analyst | C9: Secret | D9: 46091 | E9: 2600 | F9: 1450 | G9: 2540 | H9: 1600 | I9: 500 | J9: =SUM(E9:I9) | K9: 33 | L9: =IF(K9=0,0,J9/K9)
A10: Harris, Tyrone | B10: SOC Analyst | C10: TS/SCI | D10: 46096 | E10: 4800 | F10: 3850 | G10: 2740 | H10: 2400 | I10: 700 | J10: =SUM(E10:I10) | K10: 58 | L10: =IF(K10=0,0,J10/K10)
A11: Irving, Lisa | B11: Technical Writer | C11: Public Trust | D11: 46099 | E11: 1500 | F11: 485 | G11: 2140 | H11: 1000 | I11: 350 | J11: =SUM(E11:I11) | K11: 22 | L11: =IF(K11=0,0,J11/K11)
A12: Johnson, Robert | B12: Cloud Engineer | C12: Secret | D12: 46106 | E12: 4200 | F12: 1450 | G12: 2740 | H12: 2000 | I12: 550 | J12: =SUM(E12:I12) | K12: 48 | L12: =IF(K12=0,0,J12/K12)
A13: Kim, Daniel | B13: Information Assurance | C13: TS/SCI | D13: 46113 | E13: 5500 | F13: 3850 | G13: 2540 | H13: 2400 | I13: 750 | J13: =SUM(E13:I13) | K13: 75 | L13: =IF(K13=0,0,J13/K13)
A14: Lopez, Carmen | B14: Help Desk Technician | C14: Public Trust | D14: 46117 | E14: 1600 | F14: 485 | G14: 2340 | H14: 1200 | I14: 400 | J14: =SUM(E14:I14) | K14: 25 | L14: =IF(K14=0,0,J14/K14)
... A17: O'Brien, Kathleen | B17: Project Coordinator | C17: Secret | D17: 46127 | E17: 2400 | F17: 1450 | G17: 2340 | H17: 1400 | I17: 450 | J17: =SUM(E17:I17) | K17: 30 | L17: =IF(K17=0,0,J17/K17)
A20: SUMMARY STATISTICS | D20: BREAKDOWN BY POSITION TYPE
A21: Metric | B21: Value | D21: Position | E21: Count | F21: Avg Cost | G21: Avg Days
A22: Average Cost Per Hire | B22: =AVERAGE(J3:J17) | D22: Cloud Engineer | E22: =COUNTIF(B3:B17,D22) | F22: =AVERAGEIF(B3:B17,D22,J3:J17) | G22: =AVERAGEIF(B3:B17,D22,K3:K17)
A23: Median Cost Per Hire | B23: =MEDIAN(J3:J17) | D23: Cybersecurity Analyst | E23: =COUNTIF(B3:B17,D23) | F23: =AVERAGEIF(B3:B17,D23,J3:J17) | G23: =AVERAGEIF(B3:B17,D23,K3:K17)
A24: Highest Cost Hire | B24: =MAX(J3:J17) | D24: Data Analyst | E24: =COUNTIF(B3:B17,D24) | F24: =AVERAGEIF(B3:B17,D24,J3:J17) | G24: =AVERAGEIF(B3:B17,D24,K3:K17)
A25: Lowest Cost Hire | B25: =MIN(J3:J17) | D25: Database Administrator | E25: =COUNTIF(B3:B17,D25) | F25: =AVERAGEIF(B3:B17,D25,J3:J17) | G25: =AVERAGEIF(B3:B17,D25,K3:K17)
A26: Average Days to Fill | B26: =AVERAGE(K3:K17) | D26: Help Desk Technician | E26: =COUNTIF(B3:B17,D26) | F26: =AVERAGEIF(B3:B17,D26,J3:J17) | G26: =AVERAGEIF(B3:B17,D26,K3:K17)
A27: Total Hires | B27: =COUNTA(A3:A17) | D27: IT Specialist | E27: =COUNTIF(B3:B17,D27) | F27: =AVERAGEIF(B3:B17,D27,J3:J17) | G27: =AVERAGEIF(B3:B17,D27,K3:K17)
A28: Total Recruiting Spend | B28: =SUM(J3:J17) | D28: Information Assurance | E28: =COUNTIF(B3:B17,D28) | F28: =AVERAGEIF(B3:B17,D28,J3:J17) | G28: =AVERAGEIF(B3:B17,D28,K3:K17)
D29: Network Engineer | E29: =COUNTIF(B3:B17,D29) | F29: =AVERAGEIF(B3:B17,D29,J3:J17) | G29: =AVERAGEIF(B3:B17,D29,K3:K17)
D30: Program Analyst | E30: =COUNTIF(B3:B17,D30) | F30: =AVERAGEIF(B3:B17,D30,J3:J17) | G30: =AVERAGEIF(B3:B17,D30,K3:K17)
D31: Project Coordinator | E31: =COUNTIF(B3:B17,D31) | F31: =AVERAGEIF(B3:B17,D31,J3:J17) | G31: =AVERAGEIF(B3:B17,D31,K3:K17)
D32: SOC Analyst | E32: =COUNTIF(B3:B17,D32) | F32: =AVERAGEIF(B3:B17,D32,J3:J17) | G32: =AVERAGEIF(B3:B17,D32,K3:K17)
D33: Software Developer | E33: =COUNTIF(B3:B17,D33) | F33: =AVERAGEIF(B3:B17,D33,J3:J17) | G33: =AVERAGEIF(B3:B17,D33,K3:K17)
D34: Systems Administrator | E34: =COUNTIF(B3:B17,D34) | F34: =AVERAGEIF(B3:B17,D34,J3:J17) | G34: =AVERAGEIF(B3:B17,D34,K3:K17)
D35: Technical Writer | E35: =COUNTIF(B3:B17,D35) | F35: =AVERAGEIF(B3:B17,D35,J3:J17) | G35: =AVERAGEIF(B3:B17,D35,K3:K17)
D37: BREAKDOWN BY CLEARANCE LEVEL
D38: Clearance Level | E38: Count | F38: Avg Cost | G38: Avg Days
D39: Public Trust | E39: =COUNTIF(C3:C17,D39) | F39: =AVERAGEIF(C3:C17,D39,J3:J17) | G39: =AVERAGEIF(C3:C17,D39,K3:K17)
D40: Secret | E40: =COUNTIF(C3:C17,D40) | F40: =AVERAGEIF(C3:C17,D40,J3:J17) | G40: =AVERAGEIF(C3:C17,D40,K3:K17)
D41: TS/SCI | E41: =COUNTIF(C3:C17,D41) | F41: =AVERAGEIF(C3:C17,D41,J3:J17) | G41: =AVERAGEIF(C3:C17,D41,K3:K17)

Sheet Variance Report
A1: Variance Report — Budget vs Actual
A2: Category | B2: Budgeted Amount | C2: Actual Amount | D2: Variance ($) | E2: Variance (%) | F2: Status | G2: Explanation | H2: Corrective Action
A3: Recruiting | B3: =SUMIFS('Budget Plan'!F3:F35,'Budget Plan'!B3:B35,A3) | C3: =SUMIFS('Expenditure Log'!G3:G22,'Expenditure Log'!D3:D22,A3) | D3: =B3-C3 | E3: =IF(B3=0,0,D3/B3) | F3: =IF(D3<0,"Over Budget",IF(E3<=0.1,"On Track","Under Budget"))
A4: Equipment/IT | B4: =SUMIFS('Budget Plan'!F3:F35,'Budget Plan'!B3:B35,A4) | C4: =SUMIFS('Expenditure Log'!G3:G22,'Expenditure Log'!D3:D22,A4) | D4: =B4-C4 | E4: =IF(B4=0,0,D4/B4) | F4: =IF(D4<0,"Over Budget",IF(E4<=0.1,"On Track","Under Budget"))
A5: Training | B5: =SUMIFS('Budget Plan'!F3:F35,'Budget Plan'!B3:B35,A5) | C5: =SUMIFS('Expenditure Log'!G3:G22,'Expenditure Log'!D3:D22,A5) | D5: =B5-C5 | E5: =IF(B5=0,0,D5/B5) | F5: =IF(D5<0,"Over Budget",IF(E5<=0.1,"On Track","Under Budget"))
A6: Personnel | B6: =SUMIFS('Budget Plan'!F3:F35,'Budget Plan'!B3:B35,A6) | C6: =SUMIFS('Expenditure Log'!G3:G22,'Expenditure Log'!D3:D22,A6) | D6: =B6-C6 | E6: =IF(B6=0,0,D6/B6) | F6: =IF(D6<0,"Over Budget",IF(E6<=0.1,"On Track","Under Budget"))
A7: Background/Clearance | B7: =SUMIFS('Budget Plan'!F3:F35,'Budget Plan'!B3:B35,A7) | C7: =SUMIFS('Expenditure Log'!G3:G22,'Expenditure Log'!D3:D22,A7) | D7: =B7-C7 | E7: =IF(B7=0,0,D7/B7) | F7: =IF(D7<0,"Over Budget",IF(E7<=0.1,"On Track","Under Budget"))
A8: Overhead | B8: =SUMIFS('Budget Plan'!F3:F35,'Budget Plan'!B3:B35,A8) | C8: =SUMIFS('Expenditure Log'!G3:G22,'Expenditure Log'!D3:D22,A8) | D8: =B8-C8 | E8: =IF(B8=0,0,D8/B8) | F8: =IF(D8<0,"Over Budget",IF(E8<=0.1,"On Track","Under Budget"))
A9: Contingency | B9: =SUMIFS('Budget Plan'!F3:F35,'Budget Plan'!B3:B35,A9) | C9: =SUMIFS('Expenditure Log'!G3:G22,'Expenditure Log'!D3:D22,A9) | D9: =B9-C9 | E9: =IF(B9=0,0,D9/B9) | F9: =IF(D9<0,"Over Budget",IF(E9<=0.1,"On Track","Under Budget"))
A10: TOTAL | B10: =SUM(B3:B9) | C10: =SUM(C3:C9) | D10: =B10-C10 | E10: =IF(B10=0,0,D10/B10) | F10: =IF(D10<0,"Over Budget",IF(E10<=0.1,"On Track","Under Budget"))

Sheet Forecast
A1: 12-Month Forecast — Surge Hiring Budget
D2: Month 1 | E2: Month 2 | F2: Month 3 | G2: Month 4 | H2: Month 5 | I2: Month 6 | J2: Month 7 | K2: Month 8 | L2: Month 9 | M2: Month 10 | N2: Month 11 | O2: Month 12 | P2: Annual Total
A3: PLANNED SPEND
B4: Recruiting | D4: 12000 | E4: 15000 | F4: 10000 | G4: 8000 | H4: 5000 | I4: 3000 | J4: 2000 | K4: 1000 | L4: 1000 | M4: 500 | N4: 500 | O4: 500 | P4: =SUM(D4:O4)
B5: Equipment/IT | D5: 20000 | E5: 25000 | F5: 15000 | G5: 10000 | H5: 5000 | I5: 3000 | J5: 2000 | K5: 1000 | L5: 1000 | M5: 500 | N5: 500 | O5: 500 | P5: =SUM(D5:O5)
B6: Training | D6: 2000 | E6: 5000 | F6: 10000 | G6: 8000 | H6: 6000 | I6: 4000 | J6: 3000 | K6: 2000 | L6: 1500 | M6: 1000 | N6: 500 | O6: 500 | P6: =SUM(D6:O6)
B7: Personnel | D7: 5000 | E7: 20000 | F7: 45000 | G7: 50000 | H7: 50000 | I7: 50000 | J7: 50000 | K7: 50000 | L7: 50000 | M7: 50000 | N7: 50000 | O7: 50000 | P7: =SUM(D7:O7)
B8: Background/Clearance | D8: 5000 | E8: 8000 | F8: 6000 | G8: 4000 | H8: 2000 | I8: 1000 | J8: 500 | K8: 500 | L8: 500 | M8: 500 | N8: 500 | O8: 500 | P8: =SUM(D8:O8)
B9: Overhead | D9: 3000 | E9: 5000 | F9: 6000 | G9: 6000 | H9: 5000 | I9: 5000 | J9: 4000 | K9: 4000 | L9: 4000 | M9: 4000 | N9: 4000 | O9: 4000 | P9: =SUM(D9:O9)
B10: Contingency | D10: 0 | E10: 0 | F10: 0 | G10: 0 | H10: 0 | I10: 0 | J10: 0 | K10: 0 | L10: 0 | M10: 0 | N10: 0 | O10: 0 | P10: =SUM(D10:O10)
B11: Total Planned | D11: =SUM(D4:D10) | E11: =SUM(E4:E10) | F11: =SUM(F4:F10) | G11: =SUM(G4:G10) | H11: =SUM(H4:H10) | I11: =SUM(I4:I10) | J11: =SUM(J4:J10) | K11: =SUM(K4:K10) | ... O11: =SUM(O4:O10) | P11: =SUM(D11:O11)
A13: ACTUAL SPEND
B14: Recruiting | D14: 13500 | E14: 18500 | F14: 8000 | G14: 6400 | H14: 0 | I14: 0 | J14: 0 | K14: 0 | L14: 0 | M14: 0 | N14: 0 | O14: 0 | P14: =SUM(D14:O14)
B15: Equipment/IT | D15: 22000 | E15: 23700 | F15: 5250 | G15: 0 | H15: 0 | I15: 0 | J15: 0 | K15: 0 | L15: 0 | M15: 0 | N15: 0 | O15: 0 | P15: =SUM(D15:O15)
B16: Training | D16: 1500 | E16: 3000 | F16: 12000 | G16: 0 | H16: 0 | I16: 0 | J16: 0 | K16: 0 | L16: 0 | M16: 0 | N16: 0 | O16: 0 | P16: =SUM(D16:O16)
B17: Personnel | D17: 4800 | E17: 0 | F17: 67500 | G17: 45000 | H17: 0 | I17: 0 | J17: 0 | K17: 0 | L17: 0 | M17: 0 | N17: 0 | O17: 0 | P17: =SUM(D17:O17)
B18: Background/Clearance | D18: 0 | E18: 9125 | F18: 1500 | G18: 12500 | H18: 0 | I18: 0 | J18: 0 | K18: 0 | L18: 0 | M18: 0 | N18: 0 | O18: 0 | P18: =SUM(D18:O18)
B19: Overhead | D19: 0 | E19: 6600 | F19: 1650 | G19: 10000 | H19: 0 | I19: 0 | J19: 0 | K19: 0 | L19: 0 | M19: 0 | N19: 0 | O19: 0 | P19: =SUM(D19:O19)
B20: Contingency | D20: 0 | E20: 0 | F20: 0 | G20: 0 | H20: 0 | I20: 0 | J20: 0 | K20: 0 | L20: 0 | M20: 0 | N20: 0 | O20: 0 | P20: =SUM(D20:O20)
B21: Total Actual | D21: =SUM(D14:D20) | E21: =SUM(E14:E20) | F21: =SUM(F14:F20) | G21: =SUM(G14:G20) | H21: =SUM(H14:H20) | I21: =SUM(I14:I20) | J21: =SUM(J14:J20) | K21: =SUM(K14:K20) | ... O21: =SUM(O14:O20) | P21: =SUM(D21:O21)
A23: CUMULATIVE COMPARISON
B24: Cumulative Planned | D24: =D11 | E24: =D24+E11 | F24: =E24+F11 | G24: =F24+G11 | H24: =G24+H11 | I24: =H24+I11 | J24: =I24+J11 | K24: =J24+K11 | L24: =K24+L11 | ... O24: =N24+O11 | P24: =O24
B25: Cumulative Actual | D25: =D21 | E25: =D25+E21 | F25: =E25+F21 | G25: =F25+G21 | H25: =G25+H21 | I25: =H25+I21 | J25: =I25+J21 | K25: =J25+K21 | L25: =K25+L21 | ... O25: =N25+O21 | P25: =O25
B26: Cumulative Variance | D26: =D24-D25 | E26: =E24-E25 | F26: =F24-F25 | G26: =G24-G25 | H26: =H24-H25 | I26: =I24-I25 | J26: =J24-J25 | K26: =K24-K25 | ... P26: =P24-P25
A28: PROJECTIONS
A29: Metric | B29: Value
A30: Total Budget (Planned) | B30: =P24
A31: Actual Spend to Date | B31: =P25
A32: Remaining Planned | B32: =P24-P25
A33: Estimate at Completion (EAC) | B33: =P25+(P24-P25)
A34: Estimate to Complete (ETC) | B34: =P24-P25
A35: Variance at Completion (VAC) | B35: =P24-B33
A36: Cost Performance Index (CPI) | B36: =IF(P25=0,0,P24/P25)
