Workbook

Sheet Dashboard
A1: Equipment & IT Asset Tracker — Government Contract Remote Surge Hiring
A2: Dashboard Overview — Updated 04/20/2026 6:49 PM CDT
A4: ASSET SUMMARY | F4: BREAKDOWN BY EQUIPMENT TYPE
A5: Total Assets | D5: =COUNTA('Asset Inventory'!A2:A26) | F5: Equipment Type | G5: Count | H5: Deployed | I5: Value
A6: Assets Deployed | D6: =COUNTIF('Asset Inventory'!L2:L26,"Deployed") | F6: Laptop | G6: =COUNTIF('Asset Inventory'!C2:C26,F6) | H6: =COUNTIFS('Asset Inventory'!C2:C26,F6,'Asset Inventory'!L2:L26,"Deployed") | I6: =SUMIF('Asset Inventory'!C2:C26,F6,'Asset Inventory'!G2:G26)
A7: Assets In Transit | D7: =COUNTIF('Asset Inventory'!L2:L26,"Shipped") | F7: Monitor | G7: =COUNTIF('Asset Inventory'!C2:C26,F7) | H7: =COUNTIFS('Asset Inventory'!C2:C26,F7,'Asset Inventory'!L2:L26,"Deployed") | I7: =SUMIF('Asset Inventory'!C2:C26,F7,'Asset Inventory'!G2:G26)
A8: Assets In Stock | D8: =COUNTIF('Asset Inventory'!L2:L26,"In Stock") | F8: Headset | G8: =COUNTIF('Asset Inventory'!C2:C26,F8) | H8: =COUNTIFS('Asset Inventory'!C2:C26,F8,'Asset Inventory'!L2:L26,"Deployed") | I8: =SUMIF('Asset Inventory'!C2:C26,F8,'Asset Inventory'!G2:G26)
A9: Assets Configured | D9: =COUNTIF('Asset Inventory'!L2:L26,"Configured") | F9: CAC Reader | G9: =COUNTIF('Asset Inventory'!C2:C26,F9) | H9: =COUNTIFS('Asset Inventory'!C2:C26,F9,'Asset Inventory'!L2:L26,"Deployed") | I9: =SUMIF('Asset Inventory'!C2:C26,F9,'Asset Inventory'!G2:G26)
A10: Assets Pending Return | D10: =COUNTIF('Asset Inventory'!L2:L26,"Return Requested") | F10: Keyboard/Mouse | G10: =COUNTIF('Asset Inventory'!C2:C26,F10) | H10: =COUNTIFS('Asset Inventory'!C2:C26,F10,'Asset Inventory'!L2:L26,"Deployed") | I10: =SUMIF('Asset Inventory'!C2:C26,F10,'Asset Inventory'!G2:G26)
A11: Assets Returned | D11: =COUNTIF('Asset Inventory'!L2:L26,"Returned") | F11: Webcam | G11: =COUNTIF('Asset Inventory'!C2:C26,F11) | H11: =COUNTIFS('Asset Inventory'!C2:C26,F11,'Asset Inventory'!L2:L26,"Deployed") | I11: =SUMIF('Asset Inventory'!C2:C26,F11,'Asset Inventory'!G2:G26)
A12: Total Asset Value | D12: =SUM('Asset Inventory'!G2:G26) | F12: Docking Station | G12: =COUNTIF('Asset Inventory'!C2:C26,F12) | H12: =COUNTIFS('Asset Inventory'!C2:C26,F12,'Asset Inventory'!L2:L26,"Deployed") | I12: =SUMIF('Asset Inventory'!C2:C26,F12,'Asset Inventory'!G2:G26)
A13: Monthly Shipping Cost (Est.) | D13: =COUNTIF('Asset Inventory'!L2:L26,"Shipped")*35 | F13: Mobile Phone | G13: =COUNTIF('Asset Inventory'!C2:C26,F13) | H13: =COUNTIFS('Asset Inventory'!C2:C26,F13,'Asset Inventory'!L2:L26,"Deployed") | I13: =SUMIF('Asset Inventory'!C2:C26,F13,'Asset Inventory'!G2:G26)
F14: Printer | G14: =COUNTIF('Asset Inventory'!C2:C26,F14) | H14: =COUNTIFS('Asset Inventory'!C2:C26,F14,'Asset Inventory'!L2:L26,"Deployed") | I14: =SUMIF('Asset Inventory'!C2:C26,F14,'Asset Inventory'!G2:G26)
F15: Software License | G15: =COUNTIF('Asset Inventory'!C2:C26,F15) | H15: =COUNTIFS('Asset Inventory'!C2:C26,F15,'Asset Inventory'!L2:L26,"Deployed") | I15: =SUMIF('Asset Inventory'!C2:C26,F15,'Asset Inventory'!G2:G26)
A16: FULFILLMENT & READINESS | F16: Other | G16: =COUNTIF('Asset Inventory'!C2:C26,F16) | H16: =COUNTIFS('Asset Inventory'!C2:C26,F16,'Asset Inventory'!L2:L26,"Deployed") | I16: =SUMIF('Asset Inventory'!C2:C26,F16,'Asset Inventory'!G2:G26)
A17: Equipment Fulfillment Rate | D17: =IF(COUNTA('Deployment Tracker'!A2:A21)=0,0,COUNTIF('Deployment Tracker'!K2:K21,"Verified")/COUNTA('Deployment Tracker'!A2:A21)) | F17: Total | G17: =SUM(G6:G16) | H17: =SUM(H6:H16) | I17: =SUM(I6:I16)
A18: Fulfillment Status | D18: =IF(D17>=0.9,"● On Track",IF(D17>=0.7,"● Warning","● Critical"))
A19: Workspace Approval Rate | D19: =IF(COUNTA('Remote Workspace Checklist'!A2:A21)=0,0,COUNTIF('Remote Workspace Checklist'!N2:N21,"Approved")/COUNTA('Remote Workspace Checklist'!A2:A21)) | F19: STATUS DISTRIBUTION | J19: OPEN ALERTS SUMMARY
A20: Workspace Status | D20: =IF(D19>=0.8,"● On Track",IF(D19>=0.5,"● Warning","● Critical")) | F20: Status | G20: Count | J20: Priority | K20: Open | L20: In Progress
F21: In Stock | G21: =COUNTIF('Asset Inventory'!L2:L26,F21) | J21: High | K21: =COUNTIFS(Alerts!B2:B13,J21,Alerts!F2:F13,"Open") | L21: =COUNTIFS(Alerts!B2:B13,J21,Alerts!F2:F13,"In Progress")
F22: Configured | G22: =COUNTIF('Asset Inventory'!L2:L26,F22) | J22: Medium | K22: =COUNTIFS(Alerts!B2:B13,J22,Alerts!F2:F13,"Open") | L22: =COUNTIFS(Alerts!B2:B13,J22,Alerts!F2:F13,"In Progress")
A23: SHIPPING & RETURNS PERFORMANCE | F23: Shipped | G23: =COUNTIF('Asset Inventory'!L2:L26,F23) | J23: Low | K23: =COUNTIFS(Alerts!B2:B13,J23,Alerts!F2:F13,"Open") | L23: =COUNTIFS(Alerts!B2:B13,J23,Alerts!F2:F13,"In Progress")
A24: Avg Days: Order to Delivery | D24: =IFERROR(AVERAGEIF('Procurement Tracker'!R2:R16,"<>",'Procurement Tracker'!R2:R16),0) | F24: Deployed | G24: =COUNTIF('Asset Inventory'!L2:L26,F24) | J24: Total | K24: =SUM(K21:K23) | L24: =SUM(L21:L23)
A25: Overdue Returns Count | D25: =COUNTIF('Return Tracker'!R2:R9,">"&0) | F25: Return Requested | G25: =COUNTIF('Asset Inventory'!L2:L26,F25)
A26: Overdue Return Liability | D26: =SUMIF('Return Tracker'!Q2:Q9,"Escalated",'Return Tracker'!P2:P9) | F26: Returned | G26: =COUNTIF('Asset Inventory'!L2:L26,F26)
A27: Returns Compliance | D27: =IF(D25=0,"● Compliant",IF(D25<=2,"● Warning","● Non-Compliant")) | F27: Lost | G27: =COUNTIF('Asset Inventory'!L2:L26,F27)
F28: Damaged | G28: =COUNTIF('Asset Inventory'!L2:L26,F28)
F29: Disposed | G29: =COUNTIF('Asset Inventory'!L2:L26,F29)

Sheet Asset Inventory
A1: Asset ID | B1: Asset Tag | C1: Equipment Type | D1: Make/Model | E1: Serial Number | F1: Purchase Date | G1: Purchase Cost | H1: Vendor | I1: PO Number | J1: Warranty Expiration | K1: Condition | L1: Current Status | M1: Assigned To | N1: Assignment Date | O1: Location | P1: Notes
A2: AST-001 | B2: LPT-001 | C2: Laptop | D2: Dell Latitude 5540 | E2: DL5540-A1B2C3 | F2: 46032 | G2: 1249.99 | H2: Dell Technologies | I2: PO-2026-001 | J2: 47128 | K2: New | L2: Deployed | M2: Maria Santos | N2: 46068 | O2: Employee Home
A3: AST-002 | B3: LPT-002 | C3: Laptop | D3: Dell Latitude 5540 | E3: DL5540-D4E5F6 | F3: 46032 | G3: 1249.99 | H3: Dell Technologies | I3: PO-2026-001 | J3: 47128 | K3: New | L3: Deployed | M3: James Carter | N3: 46069 | O3: Employee Home
A4: AST-003 | B4: LPT-003 | C4: Laptop | D4: Dell Latitude 5540 | E4: DL5540-G7H8I9 | F4: 46032 | G4: 1249.99 | H4: Dell Technologies | I4: PO-2026-001 | J4: 47128 | K4: New | L4: Shipped | O4: In Transit | P4: Shipping to new hire
A5: AST-004 | B5: LPT-004 | C5: Laptop | D5: HP EliteBook 840 G9 | E5: HPE840-J1K2L3 | F5: 45966 | G5: 1189 | H5: HP Inc. | I5: PO-2025-042 | J5: 47062 | K5: Good | L5: Deployed | M5: Aisha Johnson | N5: 46042 | O5: Employee Home
A6: AST-005 | B6: LPT-005 | C6: Laptop | D6: HP EliteBook 840 G9 | E6: HPE840-M4N5O6 | F6: 45966 | G6: 1189 | H6: HP Inc. | I6: PO-2025-042 | J6: 47062 | K6: Good | L6: Return Requested | M6: David Kim | N6: 46044 | O6: Employee Home | P6: Separation 4/30
A7: AST-006 | B7: MON-001 | C7: Monitor | D7: Dell U2723QE 27" | E7: DLM27-P7Q8R9 | F7: 46037 | G7: 489.99 | H7: Dell Technologies | I7: PO-2026-002 | J7: 47133 | K7: New | L7: Deployed | M7: Maria Santos | N7: 46068 | O7: Employee Home
A8: AST-007 | B8: MON-002 | C8: Monitor | D8: Dell U2723QE 27" | E8: DLM27-S1T2U3 | F8: 46037 | G8: 489.99 | H8: Dell Technologies | I8: PO-2026-002 | J8: 47133 | K8: New | L8: Deployed | M8: James Carter | N8: 46069 | O8: Employee Home
A9: AST-008 | B9: MON-003 | C9: Monitor | D9: LG 27UK850-W | E9: LG27-V4W5X6 | F9: 45889 | G9: 449 | H9: CDW | I9: PO-2025-030 | J9: 46254 | K9: Good | L9: In Stock | O9: Warehouse
A10: AST-009 | B10: MON-004 | C10: Monitor | D10: LG 27UK850-W | E10: LG27-Y7Z8A1 | F10: 45889 | G10: 449 | H10: CDW | I10: PO-2025-030 | J10: 46162 | K10: Fair | L10: Returned | M10: Tom Reed | N10: 45931 | O10: Warehouse | P10: Minor scratch on bezel
A11: AST-010 | B11: HDS-001 | C11: Headset | D11: Jabra Evolve2 75 | E11: JBR75-B2C3D4 | F11: 46054 | G11: 229.99 | H11: Jabra Direct | I11: PO-2026-005 | J11: 46784 | K11: New | L11: Deployed | M11: Maria Santos | N11: 46068 | O11: Employee Home
A12: AST-011 | B12: HDS-002 | C12: Headset | D12: Jabra Evolve2 75 | E12: JBR75-E5F6G7 | F12: 46054 | G12: 229.99 | H12: Jabra Direct | I12: PO-2026-005 | J12: 46784 | K12: New | L12: Deployed | M12: Aisha Johnson | N12: 46071 | O12: Employee Home
A13: AST-012 | B13: HDS-003 | C13: Headset | D13: Poly Voyager Focus 2 | E13: PLY-H8I9J1 | F13: 45910 | G13: 199.99 | H13: CDW | I13: PO-2025-035 | J13: 46640 | K13: Good | L13: In Stock | O13: Warehouse
A14: AST-013 | B14: CAC-001 | C14: CAC Reader | D14: HID Omnikey 3121 | E14: HID-K2L3M4 | F14: 46042 | G14: 34.99 | H14: GovConnection | I14: PO-2026-003 | J14: 46772 | K14: New | L14: Deployed | M14: Maria Santos | N14: 46068 | O14: Employee Home
A15: AST-014 | B15: CAC-002 | C15: CAC Reader | D15: HID Omnikey 3121 | E15: HID-N5O6P7 | F15: 46042 | G15: 34.99 | H15: GovConnection | I15: PO-2026-003 | J15: 46772 | K15: New | L15: Deployed | M15: James Carter | N15: 46069 | O15: Employee Home
A16: AST-015 | B16: CAC-003 | C16: CAC Reader | D16: HID Omnikey 3121 | E16: HID-Q8R9S1 | F16: 46042 | G16: 34.99 | H16: GovConnection | I16: PO-2026-003 | J16: 46772 | K16: New | L16: Configured | O16: Warehouse
A17: AST-016 | B17: KBM-001 | C17: Keyboard/Mouse | D17: Logitech MK540 | E17: LOG-T2U3V4 | F17: 46047 | G17: 49.99 | H17: Amazon Business | I17: PO-2026-004 | J17: 46777 | K17: New | L17: Deployed | M17: Maria Santos | N17: 46068 | O17: Employee Home
A18: AST-017 | B18: KBM-002 | C18: Keyboard/Mouse | D18: Logitech MK540 | E18: LOG-W5X6Y7 | F18: 46047 | G18: 49.99 | H18: Amazon Business | I18: PO-2026-004 | J18: 46777 | K18: New | L18: Deployed | M18: James Carter | N18: 46069 | O18: Employee Home
A19: AST-018 | B19: WBC-001 | C19: Webcam | D19: Logitech C920s | E19: LOGC-Z8A1B2 | F19: 46058 | G19: 69.99 | H19: Amazon Business | I19: PO-2026-006 | J19: 46788 | K19: New | L19: Deployed | M19: Maria Santos | N19: 46068 | O19: Employee Home
A20: AST-019 | B20: WBC-002 | C20: Webcam | D20: Logitech C920s | E20: LOGC-C3D4E5 | F20: 46058 | G20: 69.99 | H20: Amazon Business | I20: PO-2026-006 | J20: 46788 | K20: New | L20: Shipped | O20: In Transit
A21: AST-020 | B21: DOC-001 | C21: Docking Station | D21: Dell WD22TB4 | E21: DWD-F6G7H8 | F21: 46034 | G21: 279.99 | H21: Dell Technologies | I21: PO-2026-001 | J21: 47130 | K21: New | L21: Deployed | M21: Aisha Johnson | N21: 46042 | O21: Employee Home
A22: AST-021 | B22: DOC-002 | C22: Docking Station | D22: Dell WD22TB4 | E22: DWD-I9J1K2 | F22: 46034 | G22: 279.99 | H22: Dell Technologies | I22: PO-2026-001 | J22: 47130 | K22: New | L22: In Stock | O22: Warehouse
A23: AST-022 | B23: MPH-001 | C23: Mobile Phone | D23: iPhone 15 | E23: APL-L3M4N5 | F23: 45992 | G23: 999 | H23: Apple Business | I23: PO-2025-050 | J23: 46722 | K23: Good | L23: Deployed | M23: Robert Chen | N23: 46027 | O23: Employee Home | P23: Supervisor device
A24: AST-023 | B24: PRT-001 | C24: Printer | D24: HP LaserJet Pro M404n | E24: HPP-O6P7Q8 | F24: 45823 | G24: 349 | H24: HP Inc. | I24: PO-2025-022 | J24: 46188 | K24: Fair | L24: Deployed | M24: Sarah Williams | N24: 45870 | O24: Employee Home | P24: Toner replacement needed
A25: AST-024 | B25: SWL-001 | C25: Software License | D25: Microsoft 365 E3 | E25: MS365-R9S1T2 | F25: 46023 | G25: 432 | H25: Microsoft | I25: PO-2026-010 | J25: 46388 | K25: New | L25: Deployed | M25: Maria Santos | N25: 46037 | O25: Employee Home | P25: Annual license
A26: AST-025 | B26: LPT-006 | C26: Laptop | D26: Dell Latitude 5540 | E26: DL5540-U3V4W5 | F26: 46082 | G26: 1249.99 | H26: Dell Technologies | I26: PO-2026-015 | J26: 47178 | K26: New | L26: In Stock | O26: Warehouse | P26: Reserve unit

Sheet Procurement Tracker
A1: Request ID | B1: Request Date | C1: Requested By | D1: Equipment Type | E1: Quantity | F1: Unit Cost | G1: Total Cost | H1: Vendor | I1: PO Number | J1: Order Date | K1: Expected Delivery | L1: Actual Delivery | M1: Status | N1: Approval Status | O1: Approved By | P1: Tracking Number | Q1: Carrier | R1: Days to Fulfill | S1: Notes
A2: REQ-001 | B2: 46027 | C2: Kelly Thompson | D2: Laptop | E2: 10 | F2: 1249.99 | G2: =E2*F2 | H2: Dell Technologies | I2: PO-2026-001 | J2: 46030 | K2: 46042 | L2: 46040 | M2: Received | N2: Approved | O2: Mike Davis | P2: 1Z999AA10123456784 | Q2: UPS | R2: =IF(L2="","",L2-B2) | S2: Bulk order for surge
A3: REQ-002 | B3: 46032 | C3: Kelly Thompson | D3: Monitor | E3: 10 | F3: 489.99 | G3: =E3*F3 | H3: Dell Technologies | I3: PO-2026-002 | J3: 46034 | K3: 46047 | L3: 46046 | M3: Received | N3: Approved | O3: Mike Davis | P3: 1Z999AA10123456785 | Q3: UPS | R3: =IF(L3="","",L3-B3) | S3: 27-inch monitors
A4: REQ-003 | B4: 46034 | C4: Kelly Thompson | D4: CAC Reader | E4: 20 | F4: 34.99 | G4: =E4*F4 | H4: GovConnection | I4: PO-2026-003 | J4: 46036 | K4: 46044 | L4: 46043 | M4: Received | N4: Approved | O4: Mike Davis | P4: 9400111899223100001 | Q4: USPS | R4: =IF(L4="","",L4-B4)
A5: REQ-004 | B5: 46037 | C5: Kelly Thompson | D5: Keyboard/Mouse | E5: 15 | F5: 49.99 | G5: =E5*F5 | H5: Amazon Business | I5: PO-2026-004 | J5: 46038 | K5: 46045 | L5: 46044 | M5: Received | N5: Approved | O5: Mike Davis | P5: TBA612345678901 | Q5: FedEx | R5: =IF(L5="","",L5-B5) | S5: Wireless combo sets
A6: REQ-005 | B6: 46042 | C6: Sarah Williams | D6: Headset | E6: 15 | F6: 229.99 | G6: =E6*F6 | H6: Jabra Direct | I6: PO-2026-005 | J6: 46044 | K6: 46056 | L6: 46054 | M6: Received | N6: Approved | O6: Mike Davis | P6: 1Z999AA10123456786 | Q6: UPS | R6: =IF(L6="","",L6-B6)
A7: REQ-006 | B7: 46047 | C7: Sarah Williams | D7: Webcam | E7: 10 | F7: 69.99 | G7: =E7*F7 | H7: Amazon Business | I7: PO-2026-006 | J7: 46049 | K7: 46058 | L7: 46057 | M7: Received | N7: Approved | O7: Mike Davis | P7: TBA612345678902 | Q7: FedEx | R7: =IF(L7="","",L7-B7)
A8: REQ-007 | B8: 46054 | C8: Kelly Thompson | D8: Docking Station | E8: 8 | F8: 279.99 | G8: =E8*F8 | H8: Dell Technologies | I8: PO-2026-007 | J8: 46056 | K8: 46068 | L8: 46067 | M8: Received | N8: Approved | O8: Mike Davis | P8: 1Z999AA10123456787 | Q8: UPS | R8: =IF(L8="","",L8-B8)
A9: REQ-008 | B9: 46063 | C9: Sarah Williams | D9: Laptop | E9: 5 | F9: 1249.99 | G9: =E9*F9 | H9: Dell Technologies | I9: PO-2026-008 | J9: 46065 | K9: 46078 | L9: 46077 | M9: Received | N9: Approved | O9: Mike Davis | P9: 1Z999AA10123456788 | Q9: UPS | R9: =IF(L9="","",L9-B9) | S9: Second wave hiring
A10: REQ-009 | B10: 46073 | C10: Kelly Thompson | D10: Monitor | E10: 5 | F10: 449 | G10: =E10*F10 | H10: CDW | I10: PO-2026-009 | J10: 46075 | K10: 46086 | L10: 46085 | M10: Received | N10: Approved | O10: Mike Davis | P10: 1Z999AA10123456789 | Q10: UPS | R10: =IF(L10="","",L10-B10) | S10: LG monitors
A11: REQ-010 | B11: 46082 | C11: Kelly Thompson | D11: Laptop | E11: 10 | F11: 1249.99 | G11: =E11*F11 | H11: Dell Technologies | I11: PO-2026-015 | J11: 46084 | K11: 46096 | L11: 46095 | M11: Received | N11: Approved | O11: Mike Davis | P11: 1Z999AA10123456790 | Q11: UPS | R11: =IF(L11="","",L11-B11) | S11: Third wave
A12: REQ-011 | B12: 46091 | C12: Sarah Williams | D12: Headset | E12: 10 | F12: 199.99 | G12: =E12*F12 | H12: CDW | I12: PO-2026-016 | J12: 46093 | K12: 46103 | M12: Shipped | N12: Approved | O12: Mike Davis | P12: 1Z999AA10123456791 | Q12: UPS | R12: =IF(L12="","",L12-B12) | S12: Poly headsets
A13: REQ-012 | B13: 46096 | C13: Kelly Thompson | D13: Docking Station | E13: 5 | F13: 279.99 | G13: =E13*F13 | H13: Dell Technologies | I13: PO-2026-017 | J13: 46098 | K13: 46109 | M13: Ordered | N13: Approved | O13: Mike Davis | Q13: FedEx | R13: =IF(L13="","",L13-B13)
A14: REQ-013 | B14: 46113 | C14: Sarah Williams | D14: Laptop | E14: 8 | F14: 1189 | G14: =E14*F14 | H14: HP Inc. | I14: PO-2026-020 | J14: 46115 | K14: 46130 | M14: Shipped | N14: Approved | O14: Mike Davis | P14: 774820135792468 | Q14: DHL | R14: =IF(L14="","",L14-B14) | S14: HP EliteBooks
A15: REQ-014 | B15: 46122 | C15: Kelly Thompson | D15: Webcam | E15: 10 | F15: 69.99 | G15: =E15*F15 | H15: Amazon Business | M15: Requested | N15: Pending | R15: =IF(L15="","",L15-B15) | S15: Awaiting approval
A16: REQ-015 | B16: 46127 | C16: Sarah Williams | D16: Mobile Phone | E16: 3 | F16: 999 | G16: =E16*F16 | H16: Apple Business | M16: Requested | N16: Pending | R16: =IF(L16="","",L16-B16) | S16: Supervisor phones

Sheet Deployment Tracker
A1: Employee Name | B1: Employee ID | C1: Position | D1: Start Date | E1: Kit Type | F1: Laptop Asset ID | G1: Monitor Asset ID | H1: Headset Asset ID | I1: CAC Reader Asset ID | J1: Other Equipment | K1: Kit Status | L1: Ship Date | M1: Tracking Number | N1: Carrier | O1: Expected Delivery | P1: Actual Delivery | Q1: Delivery Confirmed By | R1: Remote Workspace Verified | S1: VPN Configured | T1: All Software Installed | U1: Overall Readiness | V1: Days to Deploy | W1: Notes
A2: Maria Santos | B2: EMP-1001 | C2: Claims Examiner | D2: 46070 | E2: Standard Remote Kit | F2: AST-001 | G2: AST-006 | H2: AST-010 | I2: AST-013 | J2: KBM-001, WBC-001 | K2: Verified | L2: 46063 | M2: 1Z999AA10100001 | N2: UPS | O2: 46067 | P2: 46066 | Q2: Maria Santos | R2: Yes | S2: Yes | T2: Yes | U2: Ready | V2: =IF(P2="","",P2-D2)
A3: James Carter | B3: EMP-1002 | C3: Claims Examiner | D3: 46070 | E3: Standard Remote Kit | F3: AST-002 | G3: AST-007 | H3: AST-011 | I3: AST-014 | J3: KBM-002 | K3: Verified | L3: 46063 | M3: 1Z999AA10100002 | N3: UPS | O3: 46067 | P3: 46067 | Q3: James Carter | R3: Yes | S3: Yes | T3: Yes | U3: Ready | V3: =IF(P3="","",P3-D3)
A4: Aisha Johnson | B4: EMP-1003 | C4: Senior Claims Examiner | D4: 46049 | E4: Enhanced Remote Kit | F4: AST-004 | H4: AST-011 | I4: AST-013 | J4: DOC-001 | K4: Verified | L4: 46040 | M4: 1Z999AA10100003 | N4: UPS | O4: 46044 | P4: 46043 | Q4: Aisha Johnson | R4: Yes | S4: Yes | T4: Yes | U4: Ready | V4: =IF(P4="","",P4-D4)
A5: David Kim | B5: EMP-1004 | C5: Claims Examiner | D5: 46049 | E5: Standard Remote Kit | F5: AST-005 | G5: AST-009 | I5: CAC-003 | K5: Verified | L5: 46042 | M5: 1Z999AA10100004 | N5: UPS | O5: 46046 | P5: 46045 | Q5: David Kim | R5: Yes | S5: Yes | T5: Yes | U5: Ready | V5: =IF(P5="","",P5-D5) | W5: Separating 4/30
A6: Robert Chen | B6: EMP-1005 | C6: Supervisor | D6: 46034 | E6: Supervisor Kit | F6: AST-004 | G6: AST-008 | H6: AST-012 | I6: CAC-002 | J6: MPH-001, DOC-002 | K6: Verified | L6: 46028 | M6: 1Z999AA10100005 | N6: FedEx | O6: 46032 | P6: 46031 | Q6: Robert Chen | R6: Yes | S6: Yes | T6: Yes | U6: Ready | V6: =IF(P6="","",P6-D6)
A7: Sarah Williams | B7: EMP-1006 | C7: IT Support Lead | D7: 45870 | E7: Enhanced Remote Kit | F7: AST-004 | G7: AST-008 | H7: AST-012 | I7: CAC-003 | J7: PRT-001 | K7: Verified | L7: 45863 | M7: 1Z999AA10100006 | N7: UPS | O7: 45868 | P7: 45867 | Q7: Sarah Williams | R7: Yes | S7: Yes | T7: Yes | U7: Ready | V7: =IF(P7="","",P7-D7)
A8: Lisa Park | B8: EMP-1007 | C8: Claims Examiner | D8: 46083 | E8: Standard Remote Kit | F8: AST-025 | K8: Shipped | L8: 46078 | M8: 1Z999AA10100007 | N8: UPS | O8: 46082 | R8: Pending | S8: Pending | T8: Pending | U8: Not Ready | V8: =IF(P8="","",P8-D8) | W8: Awaiting delivery
A9: Michael Brown | B9: EMP-1008 | C9: Claims Examiner | D9: 46083 | E9: Standard Remote Kit | K9: Assembling | R9: Pending | S9: No | T9: No | U9: Not Ready | V9: =IF(P9="","",P9-D9) | W9: Kit being assembled
A10: Jennifer Liu | B10: EMP-1009 | C10: Claims Examiner | D10: 46090 | E10: Standard Remote Kit | K10: Not Started | R10: Pending | S10: No | T10: No | U10: Not Ready | V10: =IF(P10="","",P10-D10) | W10: New hire wave 3
A11: Carlos Rodriguez | B11: EMP-1010 | C11: Claims Examiner | D11: 46090 | E11: Standard Remote Kit | K11: Not Started | R11: Pending | S11: No | T11: No | U11: Not Ready | V11: =IF(P11="","",P11-D11) | W11: New hire wave 3
A12: Emma Thompson | B12: EMP-1011 | C12: Senior Claims Examiner | D12: 46097 | E12: Enhanced Remote Kit | K12: Not Started | R12: No | S12: No | T12: No | U12: Not Ready | V12: =IF(P12="","",P12-D12)
A13: Ahmed Hassan | B13: EMP-1012 | C13: Claims Examiner | D13: 46097 | E13: Standard Remote Kit | K13: Not Started | R13: Pending | S13: No | T13: No | U13: Not Ready | V13: =IF(P13="","",P13-D13)
A14: Rachel Green | B14: EMP-1013 | C14: Claims Examiner | D14: 46104 | E14: Standard Remote Kit | K14: Not Started | R14: Pending | S14: No | T14: No | U14: Not Ready | V14: =IF(P14="","",P14-D14)
A15: Tom Reed | B15: EMP-1014 | C15: Claims Examiner | D15: 46037 | E15: Standard Remote Kit | F15: AST-005 | G15: AST-009 | H15: AST-012 | I15: CAC-003 | K15: Verified | L15: 46030 | M15: 1Z999AA10100014 | N15: UPS | O15: 46034 | P15: 46034 | Q15: Tom Reed | R15: Yes | S15: Yes | T15: Yes | U15: Ready | V15: =IF(P15="","",P15-D15) | W15: Separated 3/15
A16: Nina Patel | B16: EMP-1015 | C16: Claims Examiner | D16: 46111 | E16: Standard Remote Kit | K16: Not Started | R16: Pending | S16: No | T16: No | U16: Not Ready | V16: =IF(P16="","",P16-D16)
A17: Brian Scott | B17: EMP-1016 | C17: Supervisor | D17: 46118 | E17: Supervisor Kit | K17: Not Started | R17: No | S17: No | T17: No | U17: Not Ready | V17: =IF(P17="","",P17-D17)
A18: Diana Foster | B18: EMP-1017 | C18: Claims Examiner | D18: 46118 | E18: Standard Remote Kit | K18: Not Started | R18: Pending | S18: No | T18: No | U18: Not Ready | V18: =IF(P18="","",P18-D18)
A19: Kevin Wright | B19: EMP-1018 | C19: Claims Examiner | D19: 46125 | E19: Standard Remote Kit | K19: Not Started | R19: Pending | S19: No | T19: No | U19: Not Ready | V19: =IF(P19="","",P19-D19)
A20: Laura Martinez | B20: EMP-1019 | C20: Senior Claims Examiner | D20: 46125 | E20: Enhanced Remote Kit | K20: Not Started | R20: No | S20: No | T20: No | U20: Not Ready | V20: =IF(P20="","",P20-D20)
A21: Jason Lee | B21: EMP-1020 | C21: Claims Examiner | D21: 46132 | E21: Standard Remote Kit | K21: Not Started | R21: Pending | S21: No | T21: No | U21: Not Ready | V21: =IF(P21="","",P21-D21) | W21: Starting today

Sheet Return Tracker
A1: Employee Name | B1: Employee ID | C1: Separation Date | D1: Return Initiated Date | E1: Return Deadline | F1: Assets to Return | G1: Return Kit Sent | H1: Return Shipping Label Sent | I1: Tracking Number | J1: Carrier | K1: Return Received Date | L1: Assets Received | M1: Assets Missing | N1: Condition on Return | O1: Financial Liability | P1: Liability Amount | Q1: Status | R1: Days Overdue | S1: Escalation Notes
A2: Tom Reed | B2: EMP-1014 | C2: 46096 | D2: 46097 | E2: 46111 | F2: AST-005, AST-009, AST-012, CAC-003 | G2: Yes | H2: Yes | I2: 1Z999AA10200001 | J2: UPS | K2: 46109 | L2: AST-005, AST-009, AST-012, CAC-003 | N2: Good | O2: None | P2: 0 | Q2: Complete | R2: =IF(Q2="Complete",0,IF(Q2="Written Off",0,IF(K2<>"",0,IF(TODAY()>E2,TODAY()-E2,0))))
A3: David Kim | B3: EMP-1004 | C3: 46142 | D3: 46127 | E3: 46156 | F3: AST-005, AST-009, CAC-003 | G3: Yes | H3: Yes | O3: None | P3: 0 | Q3: Pending | R3: =IF(Q3="Complete",0,IF(Q3="Written Off",0,IF(K3<>"",0,IF(TODAY()>E3,TODAY()-E3,0)))) | S3: Pre-separation initiated
A4: Angela White | B4: EMP-0998 | C4: 46081 | D4: 46082 | E4: 46095 | F4: LPT-010, MON-005, HDS-004 | G4: Yes | H4: Yes | I4: 1Z999AA10200002 | J4: UPS | K4: 46101 | L4: LPT-010, MON-005 | M4: HDS-004 | N4: Fair | O4: Partial | P4: 229.99 | Q4: Escalated | R4: =IF(Q4="Complete",0,IF(Q4="Written Off",0,IF(K4<>"",0,IF(TODAY()>E4,TODAY()-E4,0)))) | S4: Headset not returned - payroll deduction initiated
A5: Marcus Jones | B5: EMP-0995 | C5: 46053 | D5: 46054 | E5: 46067 | F5: LPT-008, MON-006, HDS-005, CAC-004 | G5: Yes | H5: Yes | I5: 1Z999AA10200003 | J5: FedEx | K5: 46065 | L5: LPT-008, MON-006, HDS-005, CAC-004 | N5: Good | O5: None | P5: 0 | Q5: Complete | R5: =IF(Q5="Complete",0,IF(Q5="Written Off",0,IF(K5<>"",0,IF(TODAY()>E5,TODAY()-E5,0))))
A6: Patricia Clark | B6: EMP-0990 | C6: 46088 | D6: 46089 | E6: 46102 | F6: LPT-009, MON-007, HDS-006, CAC-005, DOC-003 | G6: Yes | H6: Yes | I6: 1Z999AA10200004 | J6: UPS | O6: None | P6: 0 | Q6: Escalated | R6: =IF(Q6="Complete",0,IF(Q6="Written Off",0,IF(K6<>"",0,IF(TODAY()>E6,TODAY()-E6,0)))) | S6: Package lost in transit - claim filed with UPS
A7: Steven Wright | B7: EMP-0988 | C7: 46122 | D7: 46123 | E7: 46137 | F7: LPT-011, MON-008, HDS-007 | G7: Yes | H7: Yes | I7: 1Z999AA10200005 | J7: FedEx | O7: None | P7: 0 | Q7: In Transit | R7: =IF(Q7="Complete",0,IF(Q7="Written Off",0,IF(K7<>"",0,IF(TODAY()>E7,TODAY()-E7,0)))) | S7: Tracking shows in transit
A8: Nancy Taylor | B8: EMP-0985 | C8: 46101 | D8: 46102 | E8: 46115 | F8: LPT-012, MON-009, HDS-008, CAC-006 | G8: Yes | H8: Yes | I8: 9400111899223100005 | J8: USPS | K8: 46120 | L8: LPT-012, MON-009, CAC-006 | M8: HDS-008 | N8: Damaged | O8: Full | P8: 199.99 | Q8: Escalated | R8: =IF(Q8="Complete",0,IF(Q8="Written Off",0,IF(K8<>"",0,IF(TODAY()>E8,TODAY()-E8,0)))) | S8: Laptop screen cracked - full liability assessed
A9: George Adams | B9: EMP-0982 | C9: 46117 | D9: 46118 | E9: 46131 | F9: LPT-013, MON-010, HDS-009, CAC-007 | G9: No | H9: No | O9: None | P9: 0 | Q9: Pending | R9: =IF(Q9="Complete",0,IF(Q9="Written Off",0,IF(K9<>"",0,IF(TODAY()>E9,TODAY()-E9,0)))) | S9: Return kit not yet sent - awaiting address confirmation

Sheet Remote Workspace Checklist
A1: Employee Name | B1: Employee ID | C1: Dedicated Workspace | D1: Adequate Lighting | E1: Reliable Internet - Min 25 Mbps | F1: Speed Test Result | G1: Backup Internet Plan | H1: Surge Protector | I1: Ergonomic Setup | J1: Private/Secure Location | K1: Photo Submitted | L1: Verification Date | M1: Verified By | N1: Overall Status | O1: Notes
A2: Maria Santos | B2: EMP-1001 | C2: Yes | D2: Yes | E2: Yes | F2: 85 Mbps | G2: No | H2: Yes | I2: Yes | J2: Yes | K2: Yes | L2: 46067 | M2: Sarah Williams | N2: Approved
A3: James Carter | B3: EMP-1002 | C3: Yes | D3: Yes | E3: Yes | F3: 120 Mbps | G3: Yes | H3: Yes | I3: Yes | J3: Yes | K3: Yes | L3: 46067 | M3: Sarah Williams | N3: Approved
A4: Aisha Johnson | B4: EMP-1003 | C4: Yes | D4: Yes | E4: Yes | F4: 200 Mbps | G4: Yes | H4: Yes | I4: Yes | J4: Yes | K4: Yes | L4: 46041 | M4: Sarah Williams | N4: Approved | O4: Fiber connection
A5: David Kim | B5: EMP-1004 | C5: Yes | D5: Yes | E5: Yes | F5: 75 Mbps | G5: No | H5: Yes | I5: Pending | J5: Yes | K5: Yes | L5: 46041 | M5: Sarah Williams | N5: Conditional | O5: Ergonomic assessment pending
A6: Robert Chen | B6: EMP-1005 | C6: Yes | D6: Yes | E6: Yes | F6: 150 Mbps | G6: Yes | H6: Yes | I6: Yes | J6: Yes | K6: Yes | L6: 46030 | M6: Sarah Williams | N6: Approved | O6: Home office setup
A7: Sarah Williams | B7: EMP-1006 | C7: Yes | D7: Yes | E7: Yes | F7: 300 Mbps | G7: Yes | H7: Yes | I7: Yes | J7: Yes | K7: Yes | L7: 45866 | M7: Mike Davis | N7: Approved
A8: Lisa Park | B8: EMP-1007 | C8: Yes | D8: Yes | E8: Yes | F8: 50 Mbps | G8: No | H8: Yes | I8: Pending | J8: Yes | K8: No | N8: Pending Review | O8: Photo not yet submitted
A9: Michael Brown | B9: EMP-1008 | C9: Pending | D9: Pending | E9: Pending | G9: Pending | H9: Pending | I9: Pending | J9: Pending | K9: No | N9: Pending Review | O9: Not yet assessed
A10: Jennifer Liu | B10: EMP-1009 | C10: Pending | D10: Pending | E10: Pending | G10: Pending | H10: Pending | I10: Pending | J10: Pending | K10: No | N10: Pending Review | O10: New hire - wave 3
A11: Carlos Rodriguez | B11: EMP-1010 | C11: Yes | D11: Yes | E11: No | F11: 18 Mbps | G11: No | H11: No | I11: Pending | J11: Yes | K11: Yes | L11: 46086 | M11: Sarah Williams | N11: Not Approved | O11: Internet speed below minimum - needs upgrade
A12: Emma Thompson | B12: EMP-1011 | C12: Pending | D12: Pending | E12: Pending | G12: Pending | H12: Pending | I12: Pending | J12: Pending | K12: No | N12: Pending Review
A13: Ahmed Hassan | B13: EMP-1012 | C13: Yes | D13: Yes | E13: Yes | F13: 95 Mbps | G13: No | H13: Yes | I13: Yes | J13: Yes | K13: Yes | L13: 46093 | M13: Sarah Williams | N13: Approved
A14: Rachel Green | B14: EMP-1013 | C14: Pending | D14: Pending | E14: Pending | G14: Pending | H14: Pending | I14: Pending | J14: Pending | K14: No | N14: Pending Review
A15: Tom Reed | B15: EMP-1014 | C15: Yes | D15: Yes | E15: Yes | F15: 60 Mbps | G15: No | H15: Yes | I15: Yes | J15: Yes | K15: Yes | L15: 46032 | M15: Sarah Williams | N15: Approved | O15: Separated 3/15
A16: Nina Patel | B16: EMP-1015 | C16: Pending | D16: Pending | E16: Pending | G16: Pending | H16: Pending | I16: Pending | J16: Pending | K16: No | N16: Pending Review
A17: Brian Scott | B17: EMP-1016 | C17: Pending | D17: Pending | E17: Pending | G17: Pending | H17: Pending | I17: Pending | J17: Pending | K17: No | N17: Pending Review
A18: Diana Foster | B18: EMP-1017 | C18: Yes | D18: Yes | E18: Yes | F18: 110 Mbps | G18: Yes | H18: Pending | I18: Pending | J18: Yes | K18: No | N18: Pending Review | O18: Internet verified, other items pending
A19: Kevin Wright | B19: EMP-1018 | C19: Pending | D19: Pending | E19: Pending | G19: Pending | H19: Pending | I19: Pending | J19: Pending | K19: No | N19: Pending Review
A20: Laura Martinez | B20: EMP-1019 | C20: Yes | D20: No | E20: Yes | F20: 45 Mbps | G20: No | H20: Yes | I20: No | J20: Yes | K20: Yes | L20: 46122 | M20: Sarah Williams | N20: Conditional | O20: Lighting and ergonomic issues noted
A21: Jason Lee | B21: EMP-1020 | C21: Pending | D21: Pending | E21: Pending | G21: Pending | H21: Pending | I21: Pending | J21: Pending | K21: No | N21: Pending Review | O21: Starting 4/20

Sheet Alerts
A1: Alert Type | B1: Priority | C1: Description | D1: Related Asset/Employee | E1: Date Flagged | F1: Status | G1: Assigned To | H1: Resolution Notes
A2: Overdue Returns | B2: High | C2: Return package lost in transit - UPS claim filed | D2: Patricia Clark (EMP-0990) | E2: 46106 | F2: Open | G2: Sarah Williams | H2: UPS investigating - claim #CLM-887421
A3: Missing Equipment | B3: High | C3: Headset not returned with separation kit | D3: Angela White (EMP-0998) / HDS-004 | E3: 46103 | F3: In Progress | G3: Kelly Thompson | H3: Payroll deduction initiated for $229.99
A4: Warranty Expiring | B4: Medium | C4: Monitor warranty expiring within 90 days | D4: AST-009 (LG 27UK850-W) | E4: 46127 | F4: Open | G4: Sarah Williams
A5: Unfulfilled Deployments | B5: High | C5: Kit assembly not started - start date approaching | D5: Michael Brown (EMP-1008) | E5: 46122 | F5: Open | G5: Kelly Thompson | H5: Start date 3/2 - significantly overdue
A6: Workspace Not Verified | B6: Medium | C6: Internet speed below 25 Mbps minimum | D6: Carlos Rodriguez (EMP-1010) | E6: 46087 | F6: Open | G6: Sarah Williams | H6: Employee notified - ISP upgrade in progress
A7: Procurement Delays | B7: Medium | C7: Docking station order placed but no tracking yet | D7: REQ-012 / PO-2026-017 | E7: 46117 | F7: Open | G7: Kelly Thompson | H7: Contacted Dell for status update
A8: Damaged Equipment | B8: High | C8: Laptop returned with cracked screen | D8: Nancy Taylor (EMP-0985) / LPT-012 | E8: 46121 | F8: In Progress | G8: Sarah Williams | H8: Full liability assessed - $1,249.99
A9: Lost Assets | B9: High | C9: Return shipment lost - 4 assets unaccounted for | D9: Patricia Clark (EMP-0990) | E9: 46113 | F9: Open | G9: Kelly Thompson | H9: Insurance claim pending
A10: Unfulfilled Deployments | B10: Medium | C10: 10 employees in wave 3-4 have no kit assignment | D10: EMP-1009 through EMP-1020 | E10: 46127 | F10: Open | G10: Kelly Thompson | H10: Pending procurement REQ-013, REQ-014
A11: Overdue Returns | B11: Medium | C11: Return kit not sent - awaiting address confirmation | D11: George Adams (EMP-0982) | E11: 46124 | F11: Open | G11: Sarah Williams | H11: HR contacted for updated address
A12: Warranty Expiring | B12: Low | C12: Printer warranty expiring within 90 days | D12: AST-023 (HP LaserJet Pro) | E12: 46127 | F12: Open | G12: Sarah Williams
A13: Procurement Delays | B13: Medium | C13: Two procurement requests pending approval for 10+ days | D13: REQ-014, REQ-015 | E13: 46132 | F13: Open | G13: Mike Davis | H13: Escalated to contracting officer
